qvalidate/Data_Truncation_specified_columns.py
qvalidate/__init__.py
qvalidate/check_duplicate.py
qvalidate/count_validation.py
qvalidate/data_date_validation.py
qvalidate/data_number_format_val.py
qvalidate/data_validation.py
qvalidate/data_validation_precesion.py
qvalidate/meta_data_length_validation.py
qvalidate/meta_data_validation.py
qvalidate/meta_data_validation_dtype.py
qvalidate/null_validation.py
qvalidate/out_of_range.py
qvalidate/rejected_record.py
qvalidate2-0.0.1.dist-info/LICENSE
qvalidate2-0.0.1.dist-info/METADATA
qvalidate2-0.0.1.dist-info/WHEEL
qvalidate2-0.0.1.dist-info/top_level.txt
qvalidate2-0.0.1.dist-info/RECORD
