Metadata-Version: 2.1
Name: qvalidate2
Version: 0.0.1
Summary: Qvalidate2
Author: SAG
Author-email: chiragb@quinnox.com
Keywords: python,validation,ETL
Classifier: Development Status :: 4 - Beta
Classifier: Intended Audience :: Developers
Classifier: Programming Language :: Python :: 3
Classifier: Operating System :: Unix
Classifier: Operating System :: MacOS :: MacOS X
Classifier: Operating System :: Microsoft :: Windows
License-File: LICENSE
Requires-Dist: pandas >=1.0.0
